{
  "name": "pinkstuff:crystal_city/side",
  "fallback": "pinkstuff:crystal_city/rooms",
  "elements": [
    {
      "weight": 1,
      "element": {
        "element_type": "minecraft:single_pool_element",
        "projection": "rigid",
        "location": "pinkstuff:crystal_city/staircase/side1",
        "processors": "minecraft:empty",
        "override_liquid_settings": "ignore_waterlogging"
      }
    },
    {
      "weight": 1,
      "element": {
        "element_type": "minecraft:single_pool_element",
        "projection": "rigid",
        "location": "pinkstuff:crystal_city/staircase/side2",
        "processors": "minecraft:empty",
        "override_liquid_settings": "ignore_waterlogging"
      }
    },
    {
      "weight": 1,
      "element": {
        "element_type": "minecraft:single_pool_element",
        "projection": "rigid",
        "location": "pinkstuff:crystal_city/staircase/side3",
        "processors": "minecraft:empty",
        "override_liquid_settings": "ignore_waterlogging"
      }
    },
    {
      "weight": 1,
      "element": {
        "element_type": "minecraft:single_pool_element",
        "projection": "rigid",
        "location": "pinkstuff:crystal_city/staircase/side4",
        "processors": "minecraft:empty",
        "override_liquid_settings": "ignore_waterlogging"
      }
    },
    {
      "weight": 1,
      "element": {
        "element_type": "minecraft:single_pool_element",
        "projection": "rigid",
        "location": "pinkstuff:crystal_city/staircase/side5",
        "processors": "minecraft:empty",
        "override_liquid_settings": "ignore_waterlogging"
      }
    },
    {
      "weight": 1,
      "element": {
        "element_type": "minecraft:single_pool_element",
        "projection": "rigid",
        "location": "pinkstuff:crystal_city/staircase/side6",
        "processors": "minecraft:empty",
        "override_liquid_settings": "ignore_waterlogging"
      }
    },
    {
      "weight": 1,
      "element": {
        "element_type": "minecraft:single_pool_element",
        "projection": "rigid",
        "location": "pinkstuff:crystal_city/staircase/side7",
        "processors": "minecraft:empty",
        "override_liquid_settings": "ignore_waterlogging"
      }
    },
    {
      "weight": 1,
      "element": {
        "element_type": "minecraft:single_pool_element",
        "projection": "rigid",
        "location": "pinkstuff:crystal_city/staircase/side8",
        "processors": "minecraft:empty",
        "override_liquid_settings": "ignore_waterlogging"
      }
    },
    {
      "weight": 2,
      "element": {
        "element_type": "minecraft:single_pool_element",
        "projection": "rigid",
        "location": "pinkstuff:crystal_city/staircase/side9",
        "processors": "minecraft:empty",
        "override_liquid_settings": "ignore_waterlogging"
      }
    },
    {
      "weight": 2,
      "element": {
        "element_type": "minecraft:single_pool_element",
        "projection": "rigid",
        "location": "pinkstuff:crystal_city/rooms/room1",
        "processors": "minecraft:empty",
        "override_liquid_settings": "ignore_waterlogging"
      }
    },
    {
      "weight": 3,
      "element": {
        "element_type": "minecraft:single_pool_element",
        "projection": "rigid",
        "location": "pinkstuff:crystal_city/rooms/room2",
        "processors": "minecraft:empty",
        "override_liquid_settings": "ignore_waterlogging"
      }
    },
    {
      "weight": 1,
      "element": {
        "element_type": "minecraft:single_pool_element",
        "projection": "rigid",
        "location": "pinkstuff:crystal_city/rooms/room4",
        "processors": "minecraft:empty",
        "override_liquid_settings": "ignore_waterlogging"
      }
    },
    {
      "weight": 1,
      "element": {
        "element_type": "minecraft:single_pool_element",
        "projection": "rigid",
        "location": "pinkstuff:crystal_city/rooms/room5",
        "processors": "minecraft:empty",
        "override_liquid_settings": "ignore_waterlogging"
      }
    },
    {
      "weight": 1,
      "element": {
        "element_type": "minecraft:single_pool_element",
        "projection": "rigid",
        "location": "pinkstuff:crystal_city/rooms/room6",
        "processors": "minecraft:empty",
        "override_liquid_settings": "ignore_waterlogging"
      }
    },
    {
      "weight": 2,
      "element": {
        "element_type": "minecraft:single_pool_element",
        "projection": "rigid",
        "location": "pinkstuff:crystal_city/rooms/room7",
        "processors": "minecraft:empty",
        "override_liquid_settings": "ignore_waterlogging"
      }
    },
    {
      "weight": 1,
      "element": {
        "element_type": "minecraft:single_pool_element",
        "projection": "rigid",
        "location": "pinkstuff:crystal_city/rooms/room8",
        "processors": "minecraft:empty",
        "override_liquid_settings": "ignore_waterlogging"
      }
    },
    {
      "weight": 1,
      "element": {
        "element_type": "minecraft:single_pool_element",
        "projection": "rigid",
        "location": "pinkstuff:crystal_city/rooms/room9",
        "processors": "minecraft:empty",
        "override_liquid_settings": "ignore_waterlogging"
      }
    }
  ]
}